pycvcqv/__init__.py
pycvcqv/checkers.py
pycvcqv/cqv.py
pycvcqv/cv.py
pycvcqv/cv_confidence_interval.py
pycvcqv/dataframe.py
pycvcqv/formulas.py
pycvcqv/kelley.py
pycvcqv/multithread.py
pycvcqv/noncentralt.py
pycvcqv/prepare_output.py
pycvcqv/py.typed
pycvcqv/sanitizers.py
pycvcqv/singlethread.py
pycvcqv/types.py
pycvcqv/userthread.py
pycvcqv-0.1.18.dist-info/LICENSE
pycvcqv-0.1.18.dist-info/METADATA
pycvcqv-0.1.18.dist-info/WHEEL
pycvcqv-0.1.18.dist-info/RECORD
