Metadata-Version: 2.1
Name: pycvcqv
Version: 0.1.18
Summary: Coefficient of Variation (CV) and Coefficient of Quartile Variation (CQV) with Confidence Intervals (CI) 
Home-page: https://github.com/MaaniBeigy/pycvcqv
License: MIT
Keywords: coefficient of variation,coefficient of quartile variation,data science
Author: MaaniBeigy
Author-email: manibeygi@gmail.com
Requires-Python: >=3.9,<4.0
Classifier: Development Status :: 3 - Alpha
Classifier: Intended Audience :: Developers
Classifier: License :: OSI Approved :: MIT License
Classifier: Operating System :: OS Independent
Classifier: Programming Language :: Python :: 3
Classifier: Programming Language :: Python :: 3.9
Classifier: Programming Language :: Python :: 3.10
Classifier: Programming Language :: Python :: 3.11
Classifier: Programming Language :: Python :: 3.12
Classifier: Topic :: Software Development :: Libraries :: Python Modules
Requires-Dist: numpy (>=1.26.4,<2.0.0)
Requires-Dist: pandas
Requires-Dist: scipy
Project-URL: Repository, https://github.com/MaaniBeigy/pycvcqv
